{
  "id" : "AMyN-LFJS5D1yePAeV9Ym_Q",
  "timestamp" : "2026-04-24T20:30:59.428Z[UTC]",
  "appAppleId" : 6762672126,
  "cfBundleShortVersion" : "0.1.0",
  "cfBundleVersion" : "46",
  "deviceModel" : "iPhone18,2",
  "osVersion" : "26.3.1",
  "locale" : "en-US",
  "carrier" : "Xfinity Mobile",
  "timezone" : "America/New_York",
  "architecture" : "arm64e",
  "connectionStatus" : "WI_FI",
  "pairedAppleWatch" : "",
  "appUptimeMillis" : null,
  "availableDiskBytes" : 87770824704,
  "totalDiskBytes" : 255355080704,
  "networkType" : null,
  "batteryPercentage" : 45,
  "screenWidth" : 440,
  "screenHeight" : 956,
  "emailAddress" : "joe7432@aol.com",
  "comment" : "Crash66"
}